MANIFEST.in
README.txt
setup.py
adamo_calibrator/__init__.py
adamo_calibrator/calibrator.py
adamo_calibrator/constants.py
adamo_calibrator/controller.py
adamo_calibrator/export.py
adamo_calibrator/helpers.py
adamo_calibrator/run.py
adamo_calibrator/settings.py
adamo_calibrator.egg-info/PKG-INFO
adamo_calibrator.egg-info/SOURCES.txt
adamo_calibrator.egg-info/dependency_links.txt
adamo_calibrator.egg-info/entry_points.txt
adamo_calibrator.egg-info/requires.txt
adamo_calibrator.egg-info/top_level.txt
adamo_calibrator/resources/index.html
adamo_calibrator/resources/css/style.css
adamo_calibrator/resources/img/logo.png
adamo_calibrator/resources/img/puntero.png
adamo_calibrator/resources/img/puntero_confirmar.png
adamo_calibrator/resources/js/calibrator.js
adamo_calibrator/resources/js/helpers.js
adamo_calibrator/resources/js/jquery-2.0.3.min.js
adamo_calibrator/resources/js/show_hide.js
adamo_calibrator/resources/js/zaguan.js
adamo_calibrator/resources/less/style.less
adamo_calibrator/resources/locale/en_US/LC_MESSAGES/calibrator.mo
adamo_calibrator/resources/locale/en_US/LC_MESSAGES/calibrator.po
adamo_calibrator/resources/locale/es_AR/LC_MESSAGES/calibrator.mo
adamo_calibrator/resources/locale/es_AR/LC_MESSAGES/calibrator.po