Metadata-Version: 1.0
Name: adamo-calibrator
Version: 0.2.1
Summary: A touchscreen calibrator.
Home-page: https://pypi.python.org/pypi/adamo_calibrator
Author: Nicolas Illia
Author-email: nillia@msa.com.ar
License: LICENSE.txt
Platform: UNKNOWN
